{
  "zonesCrossNominees": [
    [
      {
        "inZone": [
          true,
          false
        ],
        "crossingPair": [
          {
            "time": "2020-09-13T11:10:18Z",
            "lat": 46.22728333,
            "fix": 149,
            "lng": 12.80753333,
            "alt": 892
          },
          {
            "time": "2020-09-13T11:10:19Z",
            "lat": 46.22718333,
            "fix": 150,
            "lng": 12.80765,
            "alt": 892
          }
        ]
      },
      {
        "inZone": [
          false,
          true
        ],
        "crossingPair": [
          {
            "time": "2020-09-13T11:11:06Z",
            "lat": 46.22808333,
            "fix": 197,
            "lng": 12.8106,
            "alt": 930
          },
          {
            "time": "2020-09-13T11:11:07Z",
            "lat": 46.22813333,
            "fix": 198,
            "lng": 12.81045,
            "alt": 932
          }
        ]
      },
      {
        "inZone": [
          true,
          false
        ],
        "crossingPair": [
          {
            "time": "2020-09-13T11:11:18Z",
            "lat": 46.2277,
            "fix": 209,
            "lng": 12.80936667,
            "alt": 939
          },
          {
            "time": "2020-09-13T11:11:19Z",
            "lat": 46.2276,
            "fix": 210,
            "lng": 12.8094,
            "alt": 939
          }
        ]
      },
      {
        "inZone": [
          false,
          true
        ],
        "crossingPair": [
          {
            "time": "2020-09-13T11:11:43Z",
            "lat": 46.22826667,
            "fix": 234,
            "lng": 12.81068333,
            "alt": 944
          },
          {
            "time": "2020-09-13T11:11:44Z",
            "lat": 46.22826667,
            "fix": 235,
            "lng": 12.8105,
            "alt": 945
          }
        ]
      },
      {
        "inZone": [
          true,
          false
        ],
        "crossingPair": [
          {
            "time": "2020-09-13T11:11:49Z",
            "lat": 46.22791667,
            "fix": 240,
            "lng": 12.81003333,
            "alt": 950
          },
          {
            "time": "2020-09-13T11:11:50Z",
            "lat": 46.22781667,
            "fix": 241,
            "lng": 12.81005,
            "alt": 951
          }
        ]
      },
      {
        "inZone": [
          false,
          true
        ],
        "crossingPair": [
          {
            "time": "2020-09-13T11:12:11Z",
            "lat": 46.22871667,
            "fix": 262,
            "lng": 12.81128333,
            "alt": 948
          },
          {
            "time": "2020-09-13T11:12:12Z",
            "lat": 46.22871667,
            "fix": 263,
            "lng": 12.81113333,
            "alt": 949
          }
        ]
      },
      {
        "inZone": [
          true,
          false
        ],
        "crossingPair": [
          {
            "time": "2020-09-13T11:12:18Z",
            "lat": 46.22836667,
            "fix": 269,
            "lng": 12.81075,
            "alt": 963
          },
          {
            "time": "2020-09-13T11:12:19Z",
            "lat": 46.22826667,
            "fix": 270,
            "lng": 12.81073333,
            "alt": 961
          }
        ]
      },
      {
        "inZone": [
          false,
          true
        ],
        "crossingPair": [
          {
            "time": "2020-09-13T11:12:49Z",
            "lat": 46.22945,
            "fix": 300,
            "lng": 12.81183333,
            "alt": 953
          },
          {
            "time": "2020-09-13T11:12:50Z",
            "lat": 46.22946667,
            "fix": 301,
            "lng": 12.81168333,
            "alt": 954
          }
        ]
      },
      {
        "inZone": [
          true,
          false
        ],
        "crossingPair": [
          {
            "time": "2020-09-13T11:13:09Z",
            "lat": 46.2281,
            "fix": 320,
            "lng": 12.81031667,
            "alt": 936
          },
          {
            "time": "2020-09-13T11:13:10Z",
            "lat": 46.22798333,
            "fix": 321,
            "lng": 12.81026667,
            "alt": 935
          }
        ]
      }
    ],
    [
      {
        "inZone": [
          true,
          false
        ],
        "crossingPair": [
          {
            "time": "2020-09-13T11:26:36Z",
            "lat": 46.2155,
            "fix": 1127,
            "lng": 12.84588333,
            "alt": 1303
          },
          {
            "time": "2020-09-13T11:26:37Z",
            "lat": 46.21546667,
            "fix": 1128,
            "lng": 12.84603333,
            "alt": 1303
          }
        ]
      },
      {
        "inZone": [
          false,
          true
        ],
        "crossingPair": [
          {
            "time": "2020-09-13T11:26:49Z",
            "lat": 46.21665,
            "fix": 1140,
            "lng": 12.84651667,
            "alt": 1313
          },
          {
            "time": "2020-09-13T11:26:50Z",
            "lat": 46.21671667,
            "fix": 1141,
            "lng": 12.84635,
            "alt": 1313
          }
        ]
      },
      {
        "inZone": [
          true,
          false
        ],
        "crossingPair": [
          {
            "time": "2020-09-13T11:27:13Z",
            "lat": 46.2153,
            "fix": 1164,
            "lng": 12.84593333,
            "alt": 1290
          },
          {
            "time": "2020-09-13T11:27:14Z",
            "lat": 46.21523333,
            "fix": 1165,
            "lng": 12.84605,
            "alt": 1291
          }
        ]
      },
      {
        "inZone": [
          false,
          true
        ],
        "crossingPair": [
          {
            "time": "2020-09-13T11:45:32Z",
            "lat": 46.21481667,
            "fix": 2263,
            "lng": 12.84583333,
            "alt": 1457
          },
          {
            "time": "2020-09-13T11:45:33Z",
            "lat": 46.21488333,
            "fix": 2264,
            "lng": 12.84563333,
            "alt": 1454
          }
        ]
      },
      {
        "inZone": [
          true,
          false
        ],
        "crossingPair": [
          {
            "time": "2020-09-13T11:45:59Z",
            "lat": 46.21761667,
            "fix": 2290,
            "lng": 12.84656667,
            "alt": 1432
          },
          {
            "time": "2020-09-13T11:46:00Z",
            "lat": 46.21773333,
            "fix": 2291,
            "lng": 12.84673333,
            "alt": 1431
          }
        ]
      }
    ],
    [
      {
        "inZone": [
          false,
          true
        ],
        "crossingPair": [
          {
            "time": "2020-09-13T13:07:13Z",
            "lat": 46.28903333,
            "fix": 7164,
            "lng": 13.2626,
            "alt": 1418
          },
          {
            "time": "2020-09-13T13:07:14Z",
            "lat": 46.28896667,
            "fix": 7165,
            "lng": 13.2628,
            "alt": 1416
          }
        ]
      },
      {
        "inZone": [
          true,
          false
        ],
        "crossingPair": [
          {
            "time": "2020-09-13T13:07:30Z",
            "lat": 46.28788333,
            "fix": 7181,
            "lng": 13.26275,
            "alt": 1390
          },
          {
            "time": "2020-09-13T13:07:31Z",
            "lat": 46.28791667,
            "fix": 7182,
            "lng": 13.26251667,
            "alt": 1389
          }
        ]
      }
    ],
    [],
    [],
    []
  ],
  "zonesCrossExcluded": [],
  "startSelected": [
    "2020-09-13T11:45:00Z",
    {
      "inZone": [
        true,
        false
      ],
      "crossingPair": [
        {
          "time": "2020-09-13T11:45:59Z",
          "lat": 46.21761667,
          "fix": 2290,
          "lng": 12.84656667,
          "alt": 1432
        },
        {
          "time": "2020-09-13T11:46:00Z",
          "lat": 46.21773333,
          "fix": 2291,
          "lng": 12.84673333,
          "alt": 1431
        }
      ]
    }
  ],
  "zonesCrossSelected": [
    {
      "inZone": [
        true,
        false
      ],
      "crossingPair": [
        {
          "time": "2020-09-13T11:10:18Z",
          "lat": 46.22728333,
          "fix": 149,
          "lng": 12.80753333,
          "alt": 892
        },
        {
          "time": "2020-09-13T11:10:19Z",
          "lat": 46.22718333,
          "fix": 150,
          "lng": 12.80765,
          "alt": 892
        }
      ]
    },
    {
      "inZone": [
        true,
        false
      ],
      "crossingPair": [
        {
          "time": "2020-09-13T11:45:59Z",
          "lat": 46.21761667,
          "fix": 2290,
          "lng": 12.84656667,
          "alt": 1432
        },
        {
          "time": "2020-09-13T11:46:00Z",
          "lat": 46.21773333,
          "fix": 2291,
          "lng": 12.84673333,
          "alt": 1431
        }
      ]
    },
    {
      "inZone": [
        false,
        true
      ],
      "crossingPair": [
        {
          "time": "2020-09-13T13:07:13Z",
          "lat": 46.28903333,
          "fix": 7164,
          "lng": 13.2626,
          "alt": 1418
        },
        {
          "time": "2020-09-13T13:07:14Z",
          "lat": 46.28896667,
          "fix": 7165,
          "lng": 13.2628,
          "alt": 1416
        }
      ]
    },
    null,
    null,
    null
  ],
  "startNominees": [
    [
      "2020-09-13T11:45:00Z",
      [
        {
          "inZone": [
            true,
            false
          ],
          "crossingPair": [
            {
              "time": "2020-09-13T11:45:59Z",
              "lat": 46.21761667,
              "fix": 2290,
              "lng": 12.84656667,
              "alt": 1432
            },
            {
              "time": "2020-09-13T11:46:00Z",
              "lat": 46.21773333,
              "fix": 2291,
              "lng": 12.84673333,
              "alt": 1431
            }
          ]
        }
      ]
    ]
  ]
}
