{
  "zonesCrossNominees": [
    [
      {
        "inZone": [
          true,
          false
        ],
        "crossingPair": [
          {
            "time": "2020-09-10T11:36:18Z",
            "lat": 46.22836667,
            "fix": 4313,
            "lng": 12.80316667,
            "alt": 945
          },
          {
            "time": "2020-09-10T11:36:19Z",
            "lat": 46.22831667,
            "fix": 4314,
            "lng": 12.80298333,
            "alt": 943
          }
        ]
      },
      {
        "inZone": [
          false,
          true
        ],
        "crossingPair": [
          {
            "time": "2020-09-10T11:36:31Z",
            "lat": 46.22916667,
            "fix": 4326,
            "lng": 12.80225,
            "alt": 947
          },
          {
            "time": "2020-09-10T11:36:32Z",
            "lat": 46.22918333,
            "fix": 4327,
            "lng": 12.8024,
            "alt": 946
          }
        ]
      },
      {
        "inZone": [
          true,
          false
        ],
        "crossingPair": [
          {
            "time": "2020-09-10T11:36:41Z",
            "lat": 46.22856667,
            "fix": 4336,
            "lng": 12.8029,
            "alt": 942
          },
          {
            "time": "2020-09-10T11:36:42Z",
            "lat": 46.2285,
            "fix": 4337,
            "lng": 12.80278333,
            "alt": 943
          }
        ]
      },
      {
        "inZone": [
          false,
          true
        ],
        "crossingPair": [
          {
            "time": "2020-09-10T11:36:57Z",
            "lat": 46.22936667,
            "fix": 4352,
            "lng": 12.80211667,
            "alt": 949
          },
          {
            "time": "2020-09-10T11:36:58Z",
            "lat": 46.22936667,
            "fix": 4353,
            "lng": 12.80228333,
            "alt": 949
          }
        ]
      },
      {
        "inZone": [
          true,
          false
        ],
        "crossingPair": [
          {
            "time": "2020-09-10T11:37:03Z",
            "lat": 46.22893333,
            "fix": 4358,
            "lng": 12.80261667,
            "alt": 948
          },
          {
            "time": "2020-09-10T11:37:04Z",
            "lat": 46.22883333,
            "fix": 4359,
            "lng": 12.80251667,
            "alt": 949
          }
        ]
      },
      {
        "inZone": [
          false,
          true
        ],
        "crossingPair": [
          {
            "time": "2020-09-10T11:37:14Z",
            "lat": 46.22945,
            "fix": 4369,
            "lng": 12.80205,
            "alt": 955
          },
          {
            "time": "2020-09-10T11:37:15Z",
            "lat": 46.22946667,
            "fix": 4370,
            "lng": 12.80221667,
            "alt": 955
          }
        ]
      },
      {
        "inZone": [
          true,
          false
        ],
        "crossingPair": [
          {
            "time": "2020-09-10T11:37:23Z",
            "lat": 46.22883333,
            "fix": 4378,
            "lng": 12.80263333,
            "alt": 958
          },
          {
            "time": "2020-09-10T11:37:24Z",
            "lat": 46.22876667,
            "fix": 4379,
            "lng": 12.80253333,
            "alt": 961
          }
        ]
      },
      {
        "inZone": [
          false,
          true
        ],
        "crossingPair": [
          {
            "time": "2020-09-10T11:37:34Z",
            "lat": 46.2293,
            "fix": 4389,
            "lng": 12.8021,
            "alt": 971
          },
          {
            "time": "2020-09-10T11:37:35Z",
            "lat": 46.22933333,
            "fix": 4390,
            "lng": 12.80225,
            "alt": 975
          }
        ]
      },
      {
        "inZone": [
          true,
          false
        ],
        "crossingPair": [
          {
            "time": "2020-09-10T11:37:42Z",
            "lat": 46.2288,
            "fix": 4397,
            "lng": 12.80275,
            "alt": 979
          },
          {
            "time": "2020-09-10T11:37:43Z",
            "lat": 46.2287,
            "fix": 4398,
            "lng": 12.80266667,
            "alt": 982
          }
        ]
      },
      {
        "inZone": [
          false,
          true
        ],
        "crossingPair": [
          {
            "time": "2020-09-10T11:37:55Z",
            "lat": 46.22946667,
            "fix": 4410,
            "lng": 12.80203333,
            "alt": 994
          },
          {
            "time": "2020-09-10T11:37:56Z",
            "lat": 46.22951667,
            "fix": 4411,
            "lng": 12.80218333,
            "alt": 997
          }
        ]
      },
      {
        "inZone": [
          true,
          false
        ],
        "crossingPair": [
          {
            "time": "2020-09-10T11:38:07Z",
            "lat": 46.22878333,
            "fix": 4422,
            "lng": 12.80261667,
            "alt": 1005
          },
          {
            "time": "2020-09-10T11:38:08Z",
            "lat": 46.22875,
            "fix": 4423,
            "lng": 12.80248333,
            "alt": 1007
          }
        ]
      },
      {
        "inZone": [
          false,
          true
        ],
        "crossingPair": [
          {
            "time": "2020-09-10T11:38:19Z",
            "lat": 46.22965,
            "fix": 4434,
            "lng": 12.80188333,
            "alt": 1012
          },
          {
            "time": "2020-09-10T11:38:20Z",
            "lat": 46.22971667,
            "fix": 4435,
            "lng": 12.80201667,
            "alt": 1011
          }
        ]
      },
      {
        "inZone": [
          true,
          false
        ],
        "crossingPair": [
          {
            "time": "2020-09-10T11:38:34Z",
            "lat": 46.22896667,
            "fix": 4449,
            "lng": 12.80246667,
            "alt": 1025
          },
          {
            "time": "2020-09-10T11:38:35Z",
            "lat": 46.22895,
            "fix": 4450,
            "lng": 12.80233333,
            "alt": 1026
          }
        ]
      },
      {
        "inZone": [
          false,
          true
        ],
        "crossingPair": [
          {
            "time": "2020-09-10T11:38:52Z",
            "lat": 46.22991667,
            "fix": 4467,
            "lng": 12.80175,
            "alt": 1030
          },
          {
            "time": "2020-09-10T11:38:53Z",
            "lat": 46.22986667,
            "fix": 4468,
            "lng": 12.80188333,
            "alt": 1030
          }
        ]
      },
      {
        "inZone": [
          true,
          false
        ],
        "crossingPair": [
          {
            "time": "2020-09-10T11:38:57Z",
            "lat": 46.22951667,
            "fix": 4472,
            "lng": 12.80203333,
            "alt": 1031
          },
          {
            "time": "2020-09-10T11:38:58Z",
            "lat": 46.22943333,
            "fix": 4473,
            "lng": 12.80196667,
            "alt": 1033
          }
        ]
      },
      {
        "inZone": [
          false,
          true
        ],
        "crossingPair": [
          {
            "time": "2020-09-10T11:39:21Z",
            "lat": 46.23073333,
            "fix": 4496,
            "lng": 12.80151667,
            "alt": 1040
          },
          {
            "time": "2020-09-10T11:39:22Z",
            "lat": 46.23076667,
            "fix": 4497,
            "lng": 12.8017,
            "alt": 1041
          }
        ]
      },
      {
        "inZone": [
          true,
          false
        ],
        "crossingPair": [
          {
            "time": "2020-09-10T11:43:07Z",
            "lat": 46.22966667,
            "fix": 4722,
            "lng": 12.81175,
            "alt": 1110
          },
          {
            "time": "2020-09-10T11:43:08Z",
            "lat": 46.22961667,
            "fix": 4723,
            "lng": 12.81191667,
            "alt": 1112
          }
        ]
      },
      {
        "inZone": [
          false,
          true
        ],
        "crossingPair": [
          {
            "time": "2020-09-10T11:43:19Z",
            "lat": 46.22891667,
            "fix": 4734,
            "lng": 12.81151667,
            "alt": 1122
          },
          {
            "time": "2020-09-10T11:43:20Z",
            "lat": 46.22895,
            "fix": 4735,
            "lng": 12.81131667,
            "alt": 1121
          }
        ]
      },
      {
        "inZone": [
          true,
          false
        ],
        "crossingPair": [
          {
            "time": "2020-09-10T11:43:35Z",
            "lat": 46.22973333,
            "fix": 4750,
            "lng": 12.81188333,
            "alt": 1126
          },
          {
            "time": "2020-09-10T11:43:36Z",
            "lat": 46.22966667,
            "fix": 4751,
            "lng": 12.812,
            "alt": 1124
          }
        ]
      },
      {
        "inZone": [
          false,
          true
        ],
        "crossingPair": [
          {
            "time": "2020-09-10T11:43:45Z",
            "lat": 46.22905,
            "fix": 4760,
            "lng": 12.81165,
            "alt": 1138
          },
          {
            "time": "2020-09-10T11:43:46Z",
            "lat": 46.22913333,
            "fix": 4761,
            "lng": 12.8115,
            "alt": 1136
          }
        ]
      },
      {
        "inZone": [
          true,
          false
        ],
        "crossingPair": [
          {
            "time": "2020-09-10T11:43:52Z",
            "lat": 46.22963333,
            "fix": 4767,
            "lng": 12.81188333,
            "alt": 1148
          },
          {
            "time": "2020-09-10T11:43:53Z",
            "lat": 46.22958333,
            "fix": 4768,
            "lng": 12.81201667,
            "alt": 1150
          }
        ]
      },
      {
        "inZone": [
          false,
          true
        ],
        "crossingPair": [
          {
            "time": "2020-09-10T11:44:01Z",
            "lat": 46.22896667,
            "fix": 4776,
            "lng": 12.81161667,
            "alt": 1160
          },
          {
            "time": "2020-09-10T11:44:02Z",
            "lat": 46.22898333,
            "fix": 4777,
            "lng": 12.81141667,
            "alt": 1161
          }
        ]
      },
      {
        "inZone": [
          true,
          false
        ],
        "crossingPair": [
          {
            "time": "2020-09-10T11:46:05Z",
            "lat": 46.22771667,
            "fix": 4900,
            "lng": 12.80956667,
            "alt": 1254
          },
          {
            "time": "2020-09-10T11:46:06Z",
            "lat": 46.2276,
            "fix": 4901,
            "lng": 12.8095,
            "alt": 1256
          }
        ]
      },
      {
        "inZone": [
          false,
          true
        ],
        "crossingPair": [
          {
            "time": "2020-09-10T11:46:21Z",
            "lat": 46.22716667,
            "fix": 4916,
            "lng": 12.80781667,
            "alt": 1280
          },
          {
            "time": "2020-09-10T11:46:22Z",
            "lat": 46.22726667,
            "fix": 4917,
            "lng": 12.8079,
            "alt": 1281
          }
        ]
      },
      {
        "inZone": [
          true,
          false
        ],
        "crossingPair": [
          {
            "time": "2020-09-10T11:46:25Z",
            "lat": 46.22733333,
            "fix": 4920,
            "lng": 12.80831667,
            "alt": 1281
          },
          {
            "time": "2020-09-10T11:46:26Z",
            "lat": 46.22726667,
            "fix": 4921,
            "lng": 12.80843333,
            "alt": 1281
          }
        ]
      },
      {
        "inZone": [
          false,
          true
        ],
        "crossingPair": [
          {
            "time": "2020-09-10T11:46:37Z",
            "lat": 46.22713333,
            "fix": 4932,
            "lng": 12.80708333,
            "alt": 1294
          },
          {
            "time": "2020-09-10T11:46:38Z",
            "lat": 46.22725,
            "fix": 4933,
            "lng": 12.80701667,
            "alt": 1295
          }
        ]
      },
      {
        "inZone": [
          true,
          false
        ],
        "crossingPair": [
          {
            "time": "2020-09-10T11:46:47Z",
            "lat": 46.22731667,
            "fix": 4942,
            "lng": 12.80776667,
            "alt": 1299
          },
          {
            "time": "2020-09-10T11:46:48Z",
            "lat": 46.2272,
            "fix": 4943,
            "lng": 12.80778333,
            "alt": 1299
          }
        ]
      },
      {
        "inZone": [
          false,
          true
        ],
        "crossingPair": [
          {
            "time": "2020-09-10T11:47:25Z",
            "lat": 46.22763333,
            "fix": 4980,
            "lng": 12.80431667,
            "alt": 1291
          },
          {
            "time": "2020-09-10T11:47:26Z",
            "lat": 46.22775,
            "fix": 4981,
            "lng": 12.80433333,
            "alt": 1290
          }
        ]
      },
      {
        "inZone": [
          true,
          false
        ],
        "crossingPair": [
          {
            "time": "2020-09-10T11:48:23Z",
            "lat": 46.23395,
            "fix": 5038,
            "lng": 12.80431667,
            "alt": 1215
          },
          {
            "time": "2020-09-10T11:48:24Z",
            "lat": 46.23391667,
            "fix": 5039,
            "lng": 12.80413333,
            "alt": 1216
          }
        ]
      },
      {
        "inZone": [
          false,
          true
        ],
        "crossingPair": [
          {
            "time": "2020-09-10T13:41:42Z",
            "lat": 46.22896667,
            "fix": 11837,
            "lng": 12.8023,
            "alt": 855
          },
          {
            "time": "2020-09-10T13:41:43Z",
            "lat": 46.229,
            "fix": 11838,
            "lng": 12.80246667,
            "alt": 856
          }
        ]
      },
      {
        "inZone": [
          true,
          false
        ],
        "crossingPair": [
          {
            "time": "2020-09-10T13:43:52Z",
            "lat": 46.22765,
            "fix": 11967,
            "lng": 12.8095,
            "alt": 936
          },
          {
            "time": "2020-09-10T13:43:53Z",
            "lat": 46.2276,
            "fix": 11968,
            "lng": 12.80965,
            "alt": 934
          }
        ]
      }
    ],
    [
      {
        "inZone": [
          true,
          false
        ],
        "crossingPair": [
          {
            "time": "2020-09-10T12:05:40Z",
            "lat": 46.23328333,
            "fix": 6075,
            "lng": 12.76486667,
            "alt": 1287
          },
          {
            "time": "2020-09-10T12:05:41Z",
            "lat": 46.23326667,
            "fix": 6076,
            "lng": 12.76463333,
            "alt": 1287
          }
        ]
      },
      {
        "inZone": [
          false,
          true
        ],
        "crossingPair": [
          {
            "time": "2020-09-10T12:06:38Z",
            "lat": 46.2336,
            "fix": 6133,
            "lng": 12.76428333,
            "alt": 1194
          },
          {
            "time": "2020-09-10T12:06:39Z",
            "lat": 46.23353333,
            "fix": 6134,
            "lng": 12.76455,
            "alt": 1196
          }
        ]
      },
      {
        "inZone": [
          true,
          false
        ],
        "crossingPair": [
          {
            "time": "2020-09-10T12:06:48Z",
            "lat": 46.23286667,
            "fix": 6143,
            "lng": 12.76526667,
            "alt": 1202
          },
          {
            "time": "2020-09-10T12:06:49Z",
            "lat": 46.23283333,
            "fix": 6144,
            "lng": 12.76508333,
            "alt": 1197
          }
        ]
      },
      {
        "inZone": [
          false,
          true
        ],
        "crossingPair": [
          {
            "time": "2020-09-10T12:06:55Z",
            "lat": 46.23336667,
            "fix": 6150,
            "lng": 12.76458333,
            "alt": 1186
          },
          {
            "time": "2020-09-10T12:06:56Z",
            "lat": 46.23348333,
            "fix": 6151,
            "lng": 12.76465,
            "alt": 1185
          }
        ]
      },
      {
        "inZone": [
          true,
          false
        ],
        "crossingPair": [
          {
            "time": "2020-09-10T12:29:32Z",
            "lat": 46.22323333,
            "fix": 7507,
            "lng": 12.77496667,
            "alt": 1299
          },
          {
            "time": "2020-09-10T12:29:33Z",
            "lat": 46.2231,
            "fix": 7508,
            "lng": 12.77476667,
            "alt": 1295
          }
        ]
      },
      {
        "inZone": [
          false,
          true
        ],
        "crossingPair": [
          {
            "time": "2020-09-10T13:39:25Z",
            "lat": 46.21765,
            "fix": 11700,
            "lng": 12.78051667,
            "alt": 927
          },
          {
            "time": "2020-09-10T13:39:26Z",
            "lat": 46.21771667,
            "fix": 11701,
            "lng": 12.78068333,
            "alt": 929
          }
        ]
      }
    ],
    [
      {
        "inZone": [
          false,
          true
        ],
        "crossingPair": [
          {
            "time": "2020-09-10T13:02:02Z",
            "lat": 46.16266667,
            "fix": 9457,
            "lng": 12.67438333,
            "alt": 1139
          },
          {
            "time": "2020-09-10T13:02:03Z",
            "lat": 46.16255,
            "fix": 9458,
            "lng": 12.67445,
            "alt": 1139
          }
        ]
      },
      {
        "inZone": [
          true,
          false
        ],
        "crossingPair": [
          {
            "time": "2020-09-10T13:02:12Z",
            "lat": 46.16246667,
            "fix": 9467,
            "lng": 12.67533333,
            "alt": 1118
          },
          {
            "time": "2020-09-10T13:02:13Z",
            "lat": 46.16265,
            "fix": 9468,
            "lng": 12.67538333,
            "alt": 1117
          }
        ]
      }
    ],
    [
      {
        "inZone": [
          false,
          true
        ],
        "crossingPair": [
          {
            "time": "2020-09-10T13:58:47Z",
            "lat": 46.18678333,
            "fix": 12862,
            "lng": 12.87263333,
            "alt": 887
          },
          {
            "time": "2020-09-10T13:58:48Z",
            "lat": 46.18666667,
            "fix": 12863,
            "lng": 12.87261667,
            "alt": 886
          }
        ]
      },
      {
        "inZone": [
          true,
          false
        ],
        "crossingPair": [
          {
            "time": "2020-09-10T13:58:54Z",
            "lat": 46.1863,
            "fix": 12869,
            "lng": 12.8718,
            "alt": 876
          },
          {
            "time": "2020-09-10T13:58:55Z",
            "lat": 46.18633333,
            "fix": 12870,
            "lng": 12.87161667,
            "alt": 873
          }
        ]
      }
    ],
    [
      {
        "inZone": [
          true,
          false
        ],
        "crossingPair": [
          {
            "time": "2020-09-10T11:54:39Z",
            "lat": 46.23415,
            "fix": 5414,
            "lng": 12.79495,
            "alt": 1234
          },
          {
            "time": "2020-09-10T11:54:40Z",
            "lat": 46.23415,
            "fix": 5415,
            "lng": 12.79476667,
            "alt": 1231
          }
        ]
      },
      {
        "inZone": [
          false,
          true
        ],
        "crossingPair": [
          {
            "time": "2020-09-10T12:15:02Z",
            "lat": 46.23218333,
            "fix": 6637,
            "lng": 12.79388333,
            "alt": 1070
          },
          {
            "time": "2020-09-10T12:15:03Z",
            "lat": 46.23218333,
            "fix": 6638,
            "lng": 12.79403333,
            "alt": 1071
          }
        ]
      },
      {
        "inZone": [
          true,
          false
        ],
        "crossingPair": [
          {
            "time": "2020-09-10T12:15:17Z",
            "lat": 46.232,
            "fix": 6652,
            "lng": 12.79405,
            "alt": 1087
          },
          {
            "time": "2020-09-10T12:15:18Z",
            "lat": 46.23211667,
            "fix": 6653,
            "lng": 12.79395,
            "alt": 1089
          }
        ]
      },
      {
        "inZone": [
          false,
          true
        ],
        "crossingPair": [
          {
            "time": "2020-09-10T12:15:21Z",
            "lat": 46.2325,
            "fix": 6656,
            "lng": 12.79398333,
            "alt": 1090
          },
          {
            "time": "2020-09-10T12:15:22Z",
            "lat": 46.2326,
            "fix": 6657,
            "lng": 12.79413333,
            "alt": 1089
          }
        ]
      },
      {
        "inZone": [
          true,
          false
        ],
        "crossingPair": [
          {
            "time": "2020-09-10T12:15:34Z",
            "lat": 46.23213333,
            "fix": 6669,
            "lng": 12.79406667,
            "alt": 1106
          },
          {
            "time": "2020-09-10T12:15:35Z",
            "lat": 46.23225,
            "fix": 6670,
            "lng": 12.79393333,
            "alt": 1105
          }
        ]
      },
      {
        "inZone": [
          false,
          true
        ],
        "crossingPair": [
          {
            "time": "2020-09-10T12:15:38Z",
            "lat": 46.23266667,
            "fix": 6673,
            "lng": 12.79406667,
            "alt": 1112
          },
          {
            "time": "2020-09-10T12:15:39Z",
            "lat": 46.23275,
            "fix": 6674,
            "lng": 12.7942,
            "alt": 1117
          }
        ]
      },
      {
        "inZone": [
          true,
          false
        ],
        "crossingPair": [
          {
            "time": "2020-09-10T12:15:50Z",
            "lat": 46.23235,
            "fix": 6685,
            "lng": 12.79406667,
            "alt": 1128
          },
          {
            "time": "2020-09-10T12:15:51Z",
            "lat": 46.23241667,
            "fix": 6686,
            "lng": 12.7939,
            "alt": 1129
          }
        ]
      },
      {
        "inZone": [
          false,
          true
        ],
        "crossingPair": [
          {
            "time": "2020-09-10T12:15:59Z",
            "lat": 46.23313333,
            "fix": 6694,
            "lng": 12.79421667,
            "alt": 1138
          },
          {
            "time": "2020-09-10T12:16:00Z",
            "lat": 46.23306667,
            "fix": 6695,
            "lng": 12.79435,
            "alt": 1136
          }
        ]
      },
      {
        "inZone": [
          true,
          false
        ],
        "crossingPair": [
          {
            "time": "2020-09-10T12:16:06Z",
            "lat": 46.23243333,
            "fix": 6701,
            "lng": 12.7941,
            "alt": 1143
          },
          {
            "time": "2020-09-10T12:16:07Z",
            "lat": 46.23236667,
            "fix": 6702,
            "lng": 12.79393333,
            "alt": 1143
          }
        ]
      },
      {
        "inZone": [
          false,
          true
        ],
        "crossingPair": [
          {
            "time": "2020-09-10T12:17:00Z",
            "lat": 46.23405,
            "fix": 6755,
            "lng": 12.79466667,
            "alt": 1152
          },
          {
            "time": "2020-09-10T12:17:01Z",
            "lat": 46.23406667,
            "fix": 6756,
            "lng": 12.79485,
            "alt": 1155
          }
        ]
      },
      {
        "inZone": [
          true,
          false
        ],
        "crossingPair": [
          {
            "time": "2020-09-10T12:17:21Z",
            "lat": 46.23346667,
            "fix": 6776,
            "lng": 12.79445,
            "alt": 1146
          },
          {
            "time": "2020-09-10T12:17:22Z",
            "lat": 46.23358333,
            "fix": 6777,
            "lng": 12.79433333,
            "alt": 1144
          }
        ]
      },
      {
        "inZone": [
          false,
          true
        ],
        "crossingPair": [
          {
            "time": "2020-09-10T12:17:30Z",
            "lat": 46.2343,
            "fix": 6785,
            "lng": 12.79476667,
            "alt": 1143
          },
          {
            "time": "2020-09-10T12:17:31Z",
            "lat": 46.23428333,
            "fix": 6786,
            "lng": 12.7949,
            "alt": 1143
          }
        ]
      },
      {
        "inZone": [
          true,
          false
        ],
        "crossingPair": [
          {
            "time": "2020-09-10T12:23:35Z",
            "lat": 46.23458333,
            "fix": 7150,
            "lng": 12.79511667,
            "alt": 1300
          },
          {
            "time": "2020-09-10T12:23:36Z",
            "lat": 46.23461667,
            "fix": 7151,
            "lng": 12.79493333,
            "alt": 1303
          }
        ]
      },
      {
        "inZone": [
          false,
          true
        ],
        "crossingPair": [
          {
            "time": "2020-09-10T13:41:01Z",
            "lat": 46.22593333,
            "fix": 11796,
            "lng": 12.7959,
            "alt": 870
          },
          {
            "time": "2020-09-10T13:41:02Z",
            "lat": 46.22603333,
            "fix": 11797,
            "lng": 12.79605,
            "alt": 867
          }
        ]
      },
      {
        "inZone": [
          true,
          false
        ],
        "crossingPair": [
          {
            "time": "2020-09-10T13:45:27Z",
            "lat": 46.22458333,
            "fix": 12062,
            "lng": 12.8163,
            "alt": 950
          },
          {
            "time": "2020-09-10T13:45:28Z",
            "lat": 46.22448333,
            "fix": 12063,
            "lng": 12.8164,
            "alt": 950
          }
        ]
      }
    ],
    [],
    [
      {
        "inZone": [
          false,
          true
        ],
        "crossingPair": [
          {
            "time": "2020-09-10T13:56:23Z",
            "lat": 46.20553333,
            "fix": 12718,
            "lng": 12.85521667,
            "alt": 1199
          },
          {
            "time": "2020-09-10T13:56:24Z",
            "lat": 46.2054,
            "fix": 12719,
            "lng": 12.85535,
            "alt": 1196
          }
        ]
      },
      {
        "inZone": [
          true,
          false
        ],
        "crossingPair": [
          {
            "time": "2020-09-10T13:58:00Z",
            "lat": 46.19233333,
            "fix": 12815,
            "lng": 12.86775,
            "alt": 963
          },
          {
            "time": "2020-09-10T13:58:01Z",
            "lat": 46.1922,
            "fix": 12816,
            "lng": 12.86786667,
            "alt": 961
          }
        ]
      },
      {
        "inZone": [
          false,
          true
        ],
        "crossingPair": [
          {
            "time": "2020-09-10T13:59:28Z",
            "lat": 46.19091667,
            "fix": 12903,
            "lng": 12.86661667,
            "alt": 802
          },
          {
            "time": "2020-09-10T13:59:29Z",
            "lat": 46.19108333,
            "fix": 12904,
            "lng": 12.8665,
            "alt": 799
          }
        ]
      },
      {
        "inZone": [
          true,
          false
        ],
        "crossingPair": [
          {
            "time": "2020-09-10T14:00:45Z",
            "lat": 46.20513333,
            "fix": 12980,
            "lng": 12.85933333,
            "alt": 630
          },
          {
            "time": "2020-09-10T14:00:46Z",
            "lat": 46.20533333,
            "fix": 12981,
            "lng": 12.85928333,
            "alt": 628
          }
        ]
      }
    ],
    []
  ],
  "zonesCrossExcluded": [],
  "startSelected": [
    "2020-09-10T12:00:00Z",
    {
      "inZone": [
        true,
        false
      ],
      "crossingPair": [
        {
          "time": "2020-09-10T12:29:32Z",
          "lat": 46.22323333,
          "fix": 7507,
          "lng": 12.77496667,
          "alt": 1299
        },
        {
          "time": "2020-09-10T12:29:33Z",
          "lat": 46.2231,
          "fix": 7508,
          "lng": 12.77476667,
          "alt": 1295
        }
      ]
    }
  ],
  "zonesCrossSelected": [
    {
      "inZone": [
        true,
        false
      ],
      "crossingPair": [
        {
          "time": "2020-09-10T11:36:18Z",
          "lat": 46.22836667,
          "fix": 4313,
          "lng": 12.80316667,
          "alt": 945
        },
        {
          "time": "2020-09-10T11:36:19Z",
          "lat": 46.22831667,
          "fix": 4314,
          "lng": 12.80298333,
          "alt": 943
        }
      ]
    },
    {
      "inZone": [
        true,
        false
      ],
      "crossingPair": [
        {
          "time": "2020-09-10T12:29:32Z",
          "lat": 46.22323333,
          "fix": 7507,
          "lng": 12.77496667,
          "alt": 1299
        },
        {
          "time": "2020-09-10T12:29:33Z",
          "lat": 46.2231,
          "fix": 7508,
          "lng": 12.77476667,
          "alt": 1295
        }
      ]
    },
    {
      "inZone": [
        false,
        true
      ],
      "crossingPair": [
        {
          "time": "2020-09-10T13:02:02Z",
          "lat": 46.16266667,
          "fix": 9457,
          "lng": 12.67438333,
          "alt": 1139
        },
        {
          "time": "2020-09-10T13:02:03Z",
          "lat": 46.16255,
          "fix": 9458,
          "lng": 12.67445,
          "alt": 1139
        }
      ]
    },
    {
      "inZone": [
        false,
        true
      ],
      "crossingPair": [
        {
          "time": "2020-09-10T13:58:47Z",
          "lat": 46.18678333,
          "fix": 12862,
          "lng": 12.87263333,
          "alt": 887
        },
        {
          "time": "2020-09-10T13:58:48Z",
          "lat": 46.18666667,
          "fix": 12863,
          "lng": 12.87261667,
          "alt": 886
        }
      ]
    },
    null,
    null,
    null,
    null
  ],
  "startNominees": [
    [
      "2020-09-10T12:00:00Z",
      [
        {
          "inZone": [
            true,
            false
          ],
          "crossingPair": [
            {
              "time": "2020-09-10T12:05:40Z",
              "lat": 46.23328333,
              "fix": 6075,
              "lng": 12.76486667,
              "alt": 1287
            },
            {
              "time": "2020-09-10T12:05:41Z",
              "lat": 46.23326667,
              "fix": 6076,
              "lng": 12.76463333,
              "alt": 1287
            }
          ]
        },
        {
          "inZone": [
            true,
            false
          ],
          "crossingPair": [
            {
              "time": "2020-09-10T12:06:48Z",
              "lat": 46.23286667,
              "fix": 6143,
              "lng": 12.76526667,
              "alt": 1202
            },
            {
              "time": "2020-09-10T12:06:49Z",
              "lat": 46.23283333,
              "fix": 6144,
              "lng": 12.76508333,
              "alt": 1197
            }
          ]
        },
        {
          "inZone": [
            true,
            false
          ],
          "crossingPair": [
            {
              "time": "2020-09-10T12:29:32Z",
              "lat": 46.22323333,
              "fix": 7507,
              "lng": 12.77496667,
              "alt": 1299
            },
            {
              "time": "2020-09-10T12:29:33Z",
              "lat": 46.2231,
              "fix": 7508,
              "lng": 12.77476667,
              "alt": 1295
            }
          ]
        }
      ]
    ]
  ]
}
