[
  {
    "inter": {
      "time": "2020-09-10T11:36:18.419601444829Z",
      "lat": 46.22834569,
      "fixFrac": 4313.419601444829,
      "lng": 12.80308974,
      "alt": 944.16
    },
    "cross": {
      "inZone": [
        true,
        false
      ],
      "crossingPair": [
        {
          "time": "2020-09-10T11:36:18Z",
          "lat": 46.22836667,
          "fix": 4313,
          "lng": 12.80316667,
          "alt": 945
        },
        {
          "time": "2020-09-10T11:36:19Z",
          "lat": 46.22831667,
          "fix": 4314,
          "lng": 12.80298333,
          "alt": 943
        }
      ]
    }
  },
  {
    "inter": {
      "time": "2020-09-10T12:29:32.971518704418Z",
      "lat": 46.22310385,
      "fixFrac": 7507.9715187044185,
      "lng": 12.77477229,
      "alt": 1295.11
    },
    "cross": {
      "inZone": [
        true,
        false
      ],
      "crossingPair": [
        {
          "time": "2020-09-10T12:29:32Z",
          "lat": 46.22323333,
          "fix": 7507,
          "lng": 12.77496667,
          "alt": 1299
        },
        {
          "time": "2020-09-10T12:29:33Z",
          "lat": 46.2231,
          "fix": 7508,
          "lng": 12.77476667,
          "alt": 1295
        }
      ]
    }
  },
  {
    "inter": {
      "time": "2020-09-10T13:02:02.240587793517Z",
      "lat": 46.1626386,
      "fixFrac": 9457.240587793518,
      "lng": 12.67439937,
      "alt": 1139
    },
    "cross": {
      "inZone": [
        false,
        true
      ],
      "crossingPair": [
        {
          "time": "2020-09-10T13:02:02Z",
          "lat": 46.16266667,
          "fix": 9457,
          "lng": 12.67438333,
          "alt": 1139
        },
        {
          "time": "2020-09-10T13:02:03Z",
          "lat": 46.16255,
          "fix": 9458,
          "lng": 12.67445,
          "alt": 1139
        }
      ]
    }
  },
  {
    "inter": {
      "time": "2020-09-10T13:58:47.635301594519Z",
      "lat": 46.18670922,
      "fixFrac": 12862.635301594519,
      "lng": 12.87262274,
      "alt": 886.36
    },
    "cross": {
      "inZone": [
        false,
        true
      ],
      "crossingPair": [
        {
          "time": "2020-09-10T13:58:47Z",
          "lat": 46.18678333,
          "fix": 12862,
          "lng": 12.87263333,
          "alt": 887
        },
        {
          "time": "2020-09-10T13:58:48Z",
          "lat": 46.18666667,
          "fix": 12863,
          "lng": 12.87261667,
          "alt": 886
        }
      ]
    }
  },
  null,
  null,
  null,
  null
]
