{
  "zonesCrossNominees": [
    [
      {
        "inZone": [
          true,
          false
        ],
        "crossingPair": [
          {
            "time": "2020-09-12T11:00:11Z",
            "lat": 46.22835,
            "fix": 37,
            "lng": 12.80315,
            "alt": 879
          },
          {
            "time": "2020-09-12T11:00:12Z",
            "lat": 46.22835,
            "fix": 38,
            "lng": 12.80296667,
            "alt": 876
          }
        ]
      },
      {
        "inZone": [
          false,
          true
        ],
        "crossingPair": [
          {
            "time": "2020-09-12T11:00:21Z",
            "lat": 46.22921667,
            "fix": 47,
            "lng": 12.80206667,
            "alt": 872
          },
          {
            "time": "2020-09-12T11:00:22Z",
            "lat": 46.22933333,
            "fix": 48,
            "lng": 12.80216667,
            "alt": 873
          }
        ]
      },
      {
        "inZone": [
          true,
          false
        ],
        "crossingPair": [
          {
            "time": "2020-09-12T11:00:34Z",
            "lat": 46.22881667,
            "fix": 60,
            "lng": 12.8027,
            "alt": 882
          },
          {
            "time": "2020-09-12T11:00:35Z",
            "lat": 46.22875,
            "fix": 61,
            "lng": 12.80256667,
            "alt": 878
          }
        ]
      },
      {
        "inZone": [
          false,
          true
        ],
        "crossingPair": [
          {
            "time": "2020-09-12T11:00:45Z",
            "lat": 46.22956667,
            "fix": 71,
            "lng": 12.80186667,
            "alt": 873
          },
          {
            "time": "2020-09-12T11:00:46Z",
            "lat": 46.22963333,
            "fix": 72,
            "lng": 12.80201667,
            "alt": 875
          }
        ]
      },
      {
        "inZone": [
          true,
          false
        ],
        "crossingPair": [
          {
            "time": "2020-09-12T11:00:56Z",
            "lat": 46.22918333,
            "fix": 82,
            "lng": 12.80228333,
            "alt": 873
          },
          {
            "time": "2020-09-12T11:00:57Z",
            "lat": 46.22916667,
            "fix": 83,
            "lng": 12.80208333,
            "alt": 873
          }
        ]
      },
      {
        "inZone": [
          false,
          true
        ],
        "crossingPair": [
          {
            "time": "2020-09-12T11:01:07Z",
            "lat": 46.23016667,
            "fix": 93,
            "lng": 12.80165,
            "alt": 869
          },
          {
            "time": "2020-09-12T11:01:08Z",
            "lat": 46.23023333,
            "fix": 94,
            "lng": 12.80181667,
            "alt": 869
          }
        ]
      },
      {
        "inZone": [
          true,
          false
        ],
        "crossingPair": [
          {
            "time": "2020-09-12T11:01:25Z",
            "lat": 46.22933333,
            "fix": 111,
            "lng": 12.8023,
            "alt": 863
          },
          {
            "time": "2020-09-12T11:01:26Z",
            "lat": 46.2293,
            "fix": 112,
            "lng": 12.80211667,
            "alt": 862
          }
        ]
      },
      {
        "inZone": [
          false,
          true
        ],
        "crossingPair": [
          {
            "time": "2020-09-12T11:01:52Z",
            "lat": 46.23011667,
            "fix": 138,
            "lng": 12.80175,
            "alt": 844
          },
          {
            "time": "2020-09-12T11:01:53Z",
            "lat": 46.23008333,
            "fix": 139,
            "lng": 12.80186667,
            "alt": 842
          }
        ]
      },
      {
        "inZone": [
          true,
          false
        ],
        "crossingPair": [
          {
            "time": "2020-09-12T11:02:40Z",
            "lat": 46.22728333,
            "fix": 186,
            "lng": 12.80788333,
            "alt": 814
          },
          {
            "time": "2020-09-12T11:02:41Z",
            "lat": 46.22721667,
            "fix": 187,
            "lng": 12.808,
            "alt": 814
          }
        ]
      },
      {
        "inZone": [
          false,
          true
        ],
        "crossingPair": [
          {
            "time": "2020-09-12T11:02:56Z",
            "lat": 46.22711667,
            "fix": 202,
            "lng": 12.8074,
            "alt": 807
          },
          {
            "time": "2020-09-12T11:02:57Z",
            "lat": 46.22725,
            "fix": 203,
            "lng": 12.8074,
            "alt": 808
          }
        ]
      },
      {
        "inZone": [
          true,
          false
        ],
        "crossingPair": [
          {
            "time": "2020-09-12T11:03:06Z",
            "lat": 46.2274,
            "fix": 212,
            "lng": 12.80861667,
            "alt": 821
          },
          {
            "time": "2020-09-12T11:03:07Z",
            "lat": 46.2273,
            "fix": 213,
            "lng": 12.80873333,
            "alt": 819
          }
        ]
      },
      {
        "inZone": [
          false,
          true
        ],
        "crossingPair": [
          {
            "time": "2020-09-12T11:18:47Z",
            "lat": 46.23181667,
            "fix": 1153,
            "lng": 12.81203333,
            "alt": 1505
          },
          {
            "time": "2020-09-12T11:18:48Z",
            "lat": 46.23193333,
            "fix": 1154,
            "lng": 12.8119,
            "alt": 1505
          }
        ]
      },
      {
        "inZone": [
          true,
          false
        ],
        "crossingPair": [
          {
            "time": "2020-09-12T11:18:51Z",
            "lat": 46.2323,
            "fix": 1157,
            "lng": 12.81175,
            "alt": 1502
          },
          {
            "time": "2020-09-12T11:18:52Z",
            "lat": 46.23243333,
            "fix": 1158,
            "lng": 12.81178333,
            "alt": 1500
          }
        ]
      },
      {
        "inZone": [
          false,
          true
        ],
        "crossingPair": [
          {
            "time": "2020-09-12T11:22:13Z",
            "lat": 46.22988333,
            "fix": 1359,
            "lng": 12.81208333,
            "alt": 1626
          },
          {
            "time": "2020-09-12T11:22:14Z",
            "lat": 46.22993333,
            "fix": 1360,
            "lng": 12.81188333,
            "alt": 1626
          }
        ]
      },
      {
        "inZone": [
          true,
          false
        ],
        "crossingPair": [
          {
            "time": "2020-09-12T11:22:30Z",
            "lat": 46.23106667,
            "fix": 1376,
            "lng": 12.81215,
            "alt": 1618
          },
          {
            "time": "2020-09-12T11:22:31Z",
            "lat": 46.23095,
            "fix": 1377,
            "lng": 12.81221667,
            "alt": 1618
          }
        ]
      },
      {
        "inZone": [
          false,
          true
        ],
        "crossingPair": [
          {
            "time": "2020-09-12T11:22:32Z",
            "lat": 46.23083333,
            "fix": 1378,
            "lng": 12.81221667,
            "alt": 1616
          },
          {
            "time": "2020-09-12T11:22:33Z",
            "lat": 46.23071667,
            "fix": 1379,
            "lng": 12.8122,
            "alt": 1621
          }
        ]
      },
      {
        "inZone": [
          true,
          false
        ],
        "crossingPair": [
          {
            "time": "2020-09-12T11:23:23Z",
            "lat": 46.2318,
            "fix": 1429,
            "lng": 12.80206667,
            "alt": 1548
          },
          {
            "time": "2020-09-12T11:23:24Z",
            "lat": 46.23183333,
            "fix": 1430,
            "lng": 12.8018,
            "alt": 1543
          }
        ]
      },
      {
        "inZone": [
          false,
          true
        ],
        "crossingPair": [
          {
            "time": "2020-09-12T13:20:16Z",
            "lat": 46.2312,
            "fix": 8442,
            "lng": 12.80163333,
            "alt": 906
          },
          {
            "time": "2020-09-12T13:20:17Z",
            "lat": 46.23121667,
            "fix": 8443,
            "lng": 12.80185,
            "alt": 902
          }
        ]
      },
      {
        "inZone": [
          true,
          false
        ],
        "crossingPair": [
          {
            "time": "2020-09-12T13:21:39Z",
            "lat": 46.22793333,
            "fix": 8525,
            "lng": 12.81005,
            "alt": 917
          },
          {
            "time": "2020-09-12T13:21:40Z",
            "lat": 46.2279,
            "fix": 8526,
            "lng": 12.81023333,
            "alt": 917
          }
        ]
      }
    ],
    [
      {
        "inZone": [
          false,
          true
        ],
        "crossingPair": [
          {
            "time": "2020-09-12T11:26:33Z",
            "lat": 46.23375,
            "fix": 1619,
            "lng": 12.75948333,
            "alt": 1265
          },
          {
            "time": "2020-09-12T11:26:34Z",
            "lat": 46.23375,
            "fix": 1620,
            "lng": 12.7593,
            "alt": 1266
          }
        ]
      },
      {
        "inZone": [
          true,
          false
        ],
        "crossingPair": [
          {
            "time": "2020-09-12T11:42:32Z",
            "lat": 46.24463333,
            "fix": 2578,
            "lng": 12.74421667,
            "alt": 1438
          },
          {
            "time": "2020-09-12T11:42:33Z",
            "lat": 46.24475,
            "fix": 2579,
            "lng": 12.7443,
            "alt": 1434
          }
        ]
      },
      {
        "inZone": [
          false,
          true
        ],
        "crossingPair": [
          {
            "time": "2020-09-12T11:42:47Z",
            "lat": 46.24423333,
            "fix": 2593,
            "lng": 12.74526667,
            "alt": 1419
          },
          {
            "time": "2020-09-12T11:42:48Z",
            "lat": 46.24406667,
            "fix": 2594,
            "lng": 12.74515,
            "alt": 1418
          }
        ]
      },
      {
        "inZone": [
          true,
          false
        ],
        "crossingPair": [
          {
            "time": "2020-09-12T13:13:59Z",
            "lat": 46.223,
            "fix": 8065,
            "lng": 12.77231667,
            "alt": 901
          },
          {
            "time": "2020-09-12T13:14:00Z",
            "lat": 46.22313333,
            "fix": 8066,
            "lng": 12.7724,
            "alt": 900
          }
        ]
      }
    ],
    [
      {
        "inZone": [
          false,
          true
        ],
        "crossingPair": [
          {
            "time": "2020-09-12T12:29:15Z",
            "lat": 46.10746667,
            "fix": 5381,
            "lng": 12.55663333,
            "alt": 1308
          },
          {
            "time": "2020-09-12T12:29:16Z",
            "lat": 46.10733333,
            "fix": 5382,
            "lng": 12.55651667,
            "alt": 1307
          }
        ]
      },
      {
        "inZone": [
          true,
          false
        ],
        "crossingPair": [
          {
            "time": "2020-09-12T12:29:55Z",
            "lat": 46.10801667,
            "fix": 5421,
            "lng": 12.55556667,
            "alt": 1303
          },
          {
            "time": "2020-09-12T12:29:56Z",
            "lat": 46.10815,
            "fix": 5422,
            "lng": 12.5556,
            "alt": 1305
          }
        ]
      }
    ],
    [
      {
        "inZone": [
          false,
          true
        ],
        "crossingPair": [
          {
            "time": "2020-09-12T11:28:04Z",
            "lat": 46.2368,
            "fix": 1710,
            "lng": 12.73906667,
            "alt": 1118
          },
          {
            "time": "2020-09-12T11:28:05Z",
            "lat": 46.23685,
            "fix": 1711,
            "lng": 12.73883333,
            "alt": 1114
          }
        ]
      },
      {
        "inZone": [
          true,
          false
        ],
        "crossingPair": [
          {
            "time": "2020-09-12T11:41:45Z",
            "lat": 46.24093333,
            "fix": 2531,
            "lng": 12.73715,
            "alt": 1481
          },
          {
            "time": "2020-09-12T11:41:46Z",
            "lat": 46.24101667,
            "fix": 2532,
            "lng": 12.73733333,
            "alt": 1485
          }
        ]
      },
      {
        "inZone": [
          false,
          true
        ],
        "crossingPair": [
          {
            "time": "2020-09-12T11:43:25Z",
            "lat": 46.24081667,
            "fix": 2631,
            "lng": 12.73728333,
            "alt": 1375
          },
          {
            "time": "2020-09-12T11:43:26Z",
            "lat": 46.24076667,
            "fix": 2632,
            "lng": 12.73703333,
            "alt": 1372
          }
        ]
      },
      {
        "inZone": [
          true,
          false
        ],
        "crossingPair": [
          {
            "time": "2020-09-12T12:13:01Z",
            "lat": 46.16355,
            "fix": 4407,
            "lng": 12.61311667,
            "alt": 1590
          },
          {
            "time": "2020-09-12T12:13:02Z",
            "lat": 46.16348333,
            "fix": 4408,
            "lng": 12.61293333,
            "alt": 1587
          }
        ]
      },
      {
        "inZone": [
          false,
          true
        ],
        "crossingPair": [
          {
            "time": "2020-09-12T12:46:30Z",
            "lat": 46.16368333,
            "fix": 6416,
            "lng": 12.61205,
            "alt": 1361
          },
          {
            "time": "2020-09-12T12:46:31Z",
            "lat": 46.1638,
            "fix": 6417,
            "lng": 12.61223333,
            "alt": 1359
          }
        ]
      },
      {
        "inZone": [
          true,
          false
        ],
        "crossingPair": [
          {
            "time": "2020-09-12T13:10:37Z",
            "lat": 46.20325,
            "fix": 7863,
            "lng": 12.73815,
            "alt": 1270
          },
          {
            "time": "2020-09-12T13:10:38Z",
            "lat": 46.20333333,
            "fix": 7864,
            "lng": 12.73835,
            "alt": 1266
          }
        ]
      }
    ],
    [
      {
        "inZone": [
          false,
          true
        ],
        "crossingPair": [
          {
            "time": "2020-09-12T14:33:09Z",
            "lat": 46.26978333,
            "fix": 12815,
            "lng": 13.01986667,
            "alt": 917
          },
          {
            "time": "2020-09-12T14:33:10Z",
            "lat": 46.2699,
            "fix": 12816,
            "lng": 13.01995,
            "alt": 917
          }
        ]
      },
      {
        "inZone": [
          true,
          false
        ],
        "crossingPair": [
          {
            "time": "2020-09-12T14:37:27Z",
            "lat": 46.27121667,
            "fix": 13073,
            "lng": 13.01863333,
            "alt": 917
          },
          {
            "time": "2020-09-12T14:37:28Z",
            "lat": 46.27113333,
            "fix": 13074,
            "lng": 13.01855,
            "alt": 917
          }
        ]
      },
      {
        "inZone": [
          false,
          true
        ],
        "crossingPair": [
          {
            "time": "2020-09-12T14:37:36Z",
            "lat": 46.27056667,
            "fix": 13082,
            "lng": 13.01906667,
            "alt": 917
          },
          {
            "time": "2020-09-12T14:37:37Z",
            "lat": 46.27056667,
            "fix": 13083,
            "lng": 13.01923333,
            "alt": 917
          }
        ]
      },
      {
        "inZone": [
          true,
          false
        ],
        "crossingPair": [
          {
            "time": "2020-09-12T14:41:38Z",
            "lat": 46.27098333,
            "fix": 13324,
            "lng": 13.01883333,
            "alt": 917
          },
          {
            "time": "2020-09-12T14:41:39Z",
            "lat": 46.27095,
            "fix": 13325,
            "lng": 13.01863333,
            "alt": 917
          }
        ]
      }
    ],
    [],
    [],
    []
  ],
  "zonesCrossExcluded": [],
  "startSelected": [
    "2020-09-12T11:40:00Z",
    {
      "inZone": [
        false,
        true
      ],
      "crossingPair": [
        {
          "time": "2020-09-12T11:42:47Z",
          "lat": 46.24423333,
          "fix": 2593,
          "lng": 12.74526667,
          "alt": 1419
        },
        {
          "time": "2020-09-12T11:42:48Z",
          "lat": 46.24406667,
          "fix": 2594,
          "lng": 12.74515,
          "alt": 1418
        }
      ]
    }
  ],
  "zonesCrossSelected": [
    {
      "inZone": [
        true,
        false
      ],
      "crossingPair": [
        {
          "time": "2020-09-12T11:00:11Z",
          "lat": 46.22835,
          "fix": 37,
          "lng": 12.80315,
          "alt": 879
        },
        {
          "time": "2020-09-12T11:00:12Z",
          "lat": 46.22835,
          "fix": 38,
          "lng": 12.80296667,
          "alt": 876
        }
      ]
    },
    {
      "inZone": [
        false,
        true
      ],
      "crossingPair": [
        {
          "time": "2020-09-12T11:42:47Z",
          "lat": 46.24423333,
          "fix": 2593,
          "lng": 12.74526667,
          "alt": 1419
        },
        {
          "time": "2020-09-12T11:42:48Z",
          "lat": 46.24406667,
          "fix": 2594,
          "lng": 12.74515,
          "alt": 1418
        }
      ]
    },
    {
      "inZone": [
        false,
        true
      ],
      "crossingPair": [
        {
          "time": "2020-09-12T12:29:15Z",
          "lat": 46.10746667,
          "fix": 5381,
          "lng": 12.55663333,
          "alt": 1308
        },
        {
          "time": "2020-09-12T12:29:16Z",
          "lat": 46.10733333,
          "fix": 5382,
          "lng": 12.55651667,
          "alt": 1307
        }
      ]
    },
    {
      "inZone": [
        false,
        true
      ],
      "crossingPair": [
        {
          "time": "2020-09-12T12:46:30Z",
          "lat": 46.16368333,
          "fix": 6416,
          "lng": 12.61205,
          "alt": 1361
        },
        {
          "time": "2020-09-12T12:46:31Z",
          "lat": 46.1638,
          "fix": 6417,
          "lng": 12.61223333,
          "alt": 1359
        }
      ]
    },
    {
      "inZone": [
        false,
        true
      ],
      "crossingPair": [
        {
          "time": "2020-09-12T14:33:09Z",
          "lat": 46.26978333,
          "fix": 12815,
          "lng": 13.01986667,
          "alt": 917
        },
        {
          "time": "2020-09-12T14:33:10Z",
          "lat": 46.2699,
          "fix": 12816,
          "lng": 13.01995,
          "alt": 917
        }
      ]
    },
    null,
    null,
    null
  ],
  "startNominees": [
    [
      "2020-09-12T11:40:00Z",
      [
        {
          "inZone": [
            false,
            true
          ],
          "crossingPair": [
            {
              "time": "2020-09-12T11:42:47Z",
              "lat": 46.24423333,
              "fix": 2593,
              "lng": 12.74526667,
              "alt": 1419
            },
            {
              "time": "2020-09-12T11:42:48Z",
              "lat": 46.24406667,
              "fix": 2594,
              "lng": 12.74515,
              "alt": 1418
            }
          ]
        }
      ]
    ]
  ]
}
