[
  {
    "inter": {
      "time": "2020-09-11T11:08:22.561220476096Z",
      "lat": 46.2273699,
      "fixFrac": 28.561220476096228,
      "lng": 12.80858418,
      "alt": 883
    },
    "cross": {
      "inZone": [
        true,
        false
      ],
      "crossingPair": [
        {
          "time": "2020-09-11T11:08:22Z",
          "lat": 46.22741667,
          "fix": 28,
          "lng": 12.8085,
          "alt": 883
        },
        {
          "time": "2020-09-11T11:08:23Z",
          "lat": 46.22733333,
          "fix": 29,
          "lng": 12.80865,
          "alt": 883
        }
      ]
    }
  },
  {
    "inter": {
      "time": "2020-09-11T11:48:57.007049464783Z",
      "lat": 46.21783321,
      "fixFrac": 2463.007049464784,
      "lng": 12.82858474,
      "alt": 1503.99
    },
    "cross": {
      "inZone": [
        true,
        false
      ],
      "crossingPair": [
        {
          "time": "2020-09-11T11:48:57Z",
          "lat": 46.21783333,
          "fix": 2463,
          "lng": 12.82858333,
          "alt": 1504
        },
        {
          "time": "2020-09-11T11:48:58Z",
          "lat": 46.21781667,
          "fix": 2464,
          "lng": 12.82878333,
          "alt": 1503
        }
      ]
    }
  },
  {
    "inter": {
      "time": "2020-09-11T12:18:50.168505236528Z",
      "lat": 46.27316123,
      "fixFrac": 4256.168505236528,
      "lng": 13.07171161,
      "alt": 1106
    },
    "cross": {
      "inZone": [
        false,
        true
      ],
      "crossingPair": [
        {
          "time": "2020-09-11T12:18:50Z",
          "lat": 46.27315,
          "fix": 4256,
          "lng": 13.07166667,
          "alt": 1106
        },
        {
          "time": "2020-09-11T12:18:51Z",
          "lat": 46.27321667,
          "fix": 4257,
          "lng": 13.07193333,
          "alt": 1106
        }
      ]
    }
  },
  null,
  null,
  null,
  null,
  null
]
